polars_talis/__init__.py
polars_talis/core/analyzer.py
polars_talis/core/base.py
polars_talis/indicators/momentum.py
polars_talis/indicators/trend.py
polars_talis/indicators/volatility.py
polars_talis-0.1.0.dist-info/licenses/LICENSE
polars_talis-0.1.0.dist-info/METADATA
polars_talis-0.1.0.dist-info/WHEEL
polars_talis-0.1.0.dist-info/top_level.txt
polars_talis-0.1.0.dist-info/RECORD
